README.md
setup.py
pig/__init__.py
pig/cli.py
pig/dimensions/ionic.dim.json
pig/dimensions/ios.dim.json
pig/utils/__init__.py
pig/utils/io.py
pig_py.egg-info/PKG-INFO
pig_py.egg-info/SOURCES.txt
pig_py.egg-info/dependency_links.txt
pig_py.egg-info/entry_points.txt
pig_py.egg-info/not-zip-safe
pig_py.egg-info/requires.txt
pig_py.egg-info/top_level.txt