Metadata-Version: 2.1
Name: pig-py
Version: 0.0.3
Summary: A package for generate icons for Ionic
Home-page: https://github.com/FcoJunior/pig-py
Author: Francisco Junior
Author-email: fcojunr@gmail.com
License: UNKNOWN
Platform: any
Classifier: Development Status :: 4 - Beta
Classifier: License :: OSI Approved :: MIT License
Classifier: Operating System :: POSIX
Classifier: Operating System :: MacOS
Classifier: Operating System :: Unix
Classifier: Operating System :: Microsoft :: Windows
